LICENSE
MANIFEST.in
README.md
requirements.txt
setup.py
docums_git_revision_date_localized_plugin/__init__.py
docums_git_revision_date_localized_plugin/ci.py
docums_git_revision_date_localized_plugin/exclude.py
docums_git_revision_date_localized_plugin/plugin.py
docums_git_revision_date_localized_plugin/util.py
docums_git_revision_date_localized_plugin.egg-info/PKG-INFO
docums_git_revision_date_localized_plugin.egg-info/SOURCES.txt
docums_git_revision_date_localized_plugin.egg-info/dependency_links.txt
docums_git_revision_date_localized_plugin.egg-info/entry_points.txt
docums_git_revision_date_localized_plugin.egg-info/requires.txt
docums_git_revision_date_localized_plugin.egg-info/top_level.txt
docums_git_revision_date_localized_plugin/css/timeago.css
docums_git_revision_date_localized_plugin/js/timeago.min.js
docums_git_revision_date_localized_plugin/js/timeago_docurial.js