Metadata-Version: 2.1
Name: docums-git-revision-date-localized-plugin
Version: 1.0
Summary: Docums plugin that enables displaying the localized date of the last git modification of a markdown file.
Home-page: https://github.com/khanhduy1407/docums-git-revision-date-localized-plugin
Author: NKDuy
Author-email: kn145660@gmail.com
License: MIT
Keywords: docums git date timeago babel plugin
Platform: UNKNOWN
Classifier: Programming Language :: Python :: 3
Classifier: Programming Language :: Python :: 3.7
Classifier: Programming Language :: Python :: 3.8
Classifier: Programming Language :: Python :: 3.9
Classifier: Programming Language :: Python :: 3.10
Classifier: License :: OSI Approved :: MIT License
Classifier: Operating System :: OS Independent
Requires-Python: >=3.6
License-File: LICENSE
